setup.py
akw_distributions/Binomialdistribution.py
akw_distributions/Gaussiandistribution.py
akw_distributions/Generaldistribution.py
akw_distributions/__init__.py
akw_distributions.egg-info/PKG-INFO
akw_distributions.egg-info/SOURCES.txt
akw_distributions.egg-info/dependency_links.txt
akw_distributions.egg-info/not-zip-safe
akw_distributions.egg-info/top_level.txt