Metadata-Version: 1.0
Name: akw-distributions
Version: 0.2
Summary: Gaussian distributions and Binomial distributions
Home-page: UNKNOWN
Author: Ariel Kexuan Wang
Author-email: wangkx2017@gmail.com
License: UNKNOWN
Platform: UNKNOWN
